planecompose/__init__.py
planecompose/exceptions.py
planecompose/main.py
planecompose/automations/__init__.py
planecompose/automations/actions.py
planecompose/automations/engine.py
planecompose/automations/evaluator.py
planecompose/automations/models.py
planecompose/automations/parser.py
planecompose/automations/runner.py
planecompose/automations/visualizer.py
planecompose/backend/__init__.py
planecompose/backend/base.py
planecompose/backend/plane.py
planecompose/cli/__init__.py
planecompose/cli/auth.py
planecompose/cli/automations.py
planecompose/cli/clone.py
planecompose/cli/init.py
planecompose/cli/pull.py
planecompose/cli/push.py
planecompose/cli/rate_stats.py
planecompose/cli/root.py
planecompose/cli/schema.py
planecompose/cli/status.py
planecompose/config/__init__.py
planecompose/config/context.py
planecompose/config/settings.py
planecompose/core/__init__.py
planecompose/core/models.py
planecompose/diff/__init__.py
planecompose/parser/__init__.py
planecompose/parser/labels_yaml.py
planecompose/parser/plane_yaml.py
planecompose/parser/types_yaml.py
planecompose/parser/work_yaml.py
planecompose/parser/workflows_yaml.py
planecompose/sync/__init__.py
planecompose/utils/__init__.py
planecompose/utils/errors.py
planecompose/utils/http_client.py
planecompose/utils/logger.py
planecompose/utils/project.py
planecompose/utils/rate_limit.py
planecompose/utils/work_items.py
planecompose/validation/__init__.py
plane_compose-0.2.0.dist-info/METADATA
plane_compose-0.2.0.dist-info/WHEEL
plane_compose-0.2.0.dist-info/entry_points.txt
plane_compose-0.2.0.dist-info/licenses/LICENSE.txt
plane_compose-0.2.0.dist-info/RECORD
