Metadata-Version: 2.4
Name: plane-compose
Version: 0.2.0
Summary: Project as Code framework for Plane - Define and sync projects declaratively with YAML
Project-URL: Homepage, https://github.com/makeplane/compose
Project-URL: Documentation, https://github.com/makeplane/compose/tree/main/docs
Project-URL: Repository, https://github.com/makeplane/compose
Project-URL: Bug Tracker, https://github.com/makeplane/compose/issues
Project-URL: Source Code, https://github.com/makeplane/compose
Author-email: "Plane Software, Inc." <hello@plane.so>
Maintainer-email: "Plane Software, Inc." <hello@plane.so>
License: AGPL-3.0-or-later
License-File: LICENSE.txt
Keywords: automation,cli,devops,infrastructure-as-code,issue-tracking,plane,project-management,workflow,yaml
Classifier: Development Status :: 4 - Beta
Classifier: Environment :: Console
Classifier: Intended Audience :: Developers
Classifier: License :: OSI Approved :: GNU Affero General Public License v3 or later (AGPLv3+)
Classifier: Operating System :: OS Independent
Classifier: Programming Language :: Python :: 3
Classifier: Programming Language :: Python :: 3.10
Classifier: Programming Language :: Python :: 3.11
Classifier: Programming Language :: Python :: 3.12
Classifier: Topic :: Software Development :: Build Tools
Classifier: Topic :: Software Development :: Libraries :: Python Modules
Classifier: Typing :: Typed
Requires-Python: >=3.10
Requires-Dist: cel-python>=0.4.0
Requires-Dist: httpx>=0.25.0
Requires-Dist: plane-sdk>=0.1.10
Requires-Dist: pydantic-settings>=2.0.0
Requires-Dist: pydantic>=2.0.0
Requires-Dist: python-dotenv>=1.0.0
Requires-Dist: pyyaml>=6.0
Requires-Dist: rich>=13.0.0
Requires-Dist: typer[all]>=0.9.0
Provides-Extra: dev
Requires-Dist: mypy>=1.0.0; extra == 'dev'
Requires-Dist: pytest-asyncio>=0.21.0; extra == 'dev'
Requires-Dist: pytest-cov>=4.0.0; extra == 'dev'
Requires-Dist: pytest>=7.0.0; extra == 'dev'
Requires-Dist: ruff>=0.1.0; extra == 'dev'
